{
    "version": "https://jsonfeed.org/version/1",
    "title": "Mawchu 貓奴前端的天空 • All posts by \"hexo\" tag",
    "description": "Mawchu 貓奴前端，為熱愛平面設計與貓咪的前端工程師 - 謝佳芳（毛球）的技術部落格，喜歡撰寫技術文章幫助自己在前端之路成長，涉及 Javascript、Vue、Laravel 與其他程式相關的討論與學習",
    "home_page_url": "http://maomaoxie.github.io",
    "items": [
        {
            "id": "http://maomaoxie.github.io/2022/08/05/hexo-rss/",
            "url": "http://maomaoxie.github.io/2022/08/05/hexo-rss/",
            "title": "Hexo RSS 自動產生器",
            "date_published": "2022-08-05T07:39:34.000Z",
            "content_html": "<html><head></head><body><p>RSS 訂閱功能越來越夯，可以即時通知訂閱戶更新的文章內容，增加回流的流量與網站的熱度，chrome 也有提供 RSS reader 的外掛功能直接讀取 RSS 檔案。<br>既然建立好了自己的部落格怎麼可以沒有 RSS XD?</p>\n<p>先前在專案包嘗試使用 hexo-generator-feed 套件，但是建立出來的 atom.xml 檔案會出現亂碼，後來找到一個套件甚至支援 json 與 rss 格式：</p>\n<h1 id=\"安裝-Hexo-seed-套件\"><a href=\"#安裝-Hexo-seed-套件\" class=\"headerlink\" title=\"安裝 Hexo seed 套件\"></a>安裝 Hexo seed 套件</h1><figure class=\"highlight javascript hljs\"><table><tbody><tr><td class=\"gutter\"><pre><span class=\"line\">1</span><br></pre></td><td class=\"code\"><pre><span class=\"line\">npm install --save hexo-feed</span><br></pre></td></tr></tbody></table></figure>\n\n<h3 id=\"檔案格式\"><a href=\"#檔案格式\" class=\"headerlink\" title=\"檔案格式\"></a>檔案格式</h3><p>hexo-feed 可以設定三種文件格式：atom、json 還有 rss，建立的模板可以透過專案包根目錄的 _config.yml 去設定模板的 path（template）：</p>\n<figure class=\"highlight javascript hljs\"><figcaption><span>_config.yml</span></figcaption><table><tbody><tr><td class=\"gutter\"><pre><span class=\"line\">1</span><br><span class=\"line\">2</span><br><span class=\"line\">3</span><br><span class=\"line\">4</span><br><span class=\"line\">5</span><br><span class=\"line\">6</span><br><span class=\"line\">7</span><br><span class=\"line\">8</span><br><span class=\"line\">9</span><br><span class=\"line\">10</span><br><span class=\"line\">11</span><br><span class=\"line\">12</span><br><span class=\"line\">13</span><br><span class=\"line\">14</span><br><span class=\"line\">15</span><br><span class=\"line\">16</span><br><span class=\"line\">17</span><br></pre></td><td class=\"code\"><pre><span class=\"line\"><span class=\"hljs-attr\">feed</span>:</span><br><span class=\"line\">    <span class=\"hljs-attr\">limit</span>: <span class=\"hljs-number\">20</span></span><br><span class=\"line\">    <span class=\"hljs-attr\">order_by</span>: <span class=\"hljs-string\">\"-date\"</span></span><br><span class=\"line\">    <span class=\"hljs-attr\">tag_dir</span>: <span class=\"hljs-string\">\"tag\"</span></span><br><span class=\"line\">    <span class=\"hljs-attr\">category_dir</span>: <span class=\"hljs-string\">\"category\"</span></span><br><span class=\"line\">    <span class=\"hljs-attr\">rss</span>:</span><br><span class=\"line\">        <span class=\"hljs-attr\">enable</span>: <span class=\"hljs-literal\">true</span></span><br><span class=\"line\">        <span class=\"hljs-attr\">template</span>: <span class=\"hljs-string\">\"themes/layout/template/rss.ejs\"</span> </span><br><span class=\"line\">        <span class=\"hljs-attr\">output</span>: <span class=\"hljs-string\">\"rss.xml\"</span></span><br><span class=\"line\">    <span class=\"hljs-attr\">atom</span>:</span><br><span class=\"line\">        <span class=\"hljs-attr\">enable</span>: <span class=\"hljs-literal\">true</span></span><br><span class=\"line\">        <span class=\"hljs-attr\">template</span>: <span class=\"hljs-string\">\"themes/layout/template/atom.ejs\"</span></span><br><span class=\"line\">        <span class=\"hljs-attr\">output</span>: <span class=\"hljs-string\">\"atom.xml\"</span></span><br><span class=\"line\">    <span class=\"hljs-attr\">jsonFeed</span>:</span><br><span class=\"line\">        <span class=\"hljs-attr\">enable</span>: <span class=\"hljs-literal\">true</span></span><br><span class=\"line\">        <span class=\"hljs-attr\">template</span>: <span class=\"hljs-string\">\"themes/layout/template/json.ejs\"</span></span><br><span class=\"line\">        <span class=\"hljs-attr\">output</span>: <span class=\"hljs-string\">\"feed.json\"</span></span><br></pre></td></tr></tbody></table></figure>\n\n<h3 id=\"模板內容\"><a href=\"#模板內容\" class=\"headerlink\" title=\"模板內容\"></a>模板內容</h3><figure class=\"highlight javascript hljs\"><figcaption><span>atom</span></figcaption><table><tbody><tr><td class=\"gutter\"><pre><span class=\"line\">1</span><br><span class=\"line\">2</span><br><span class=\"line\">3</span><br><span class=\"line\">4</span><br><span class=\"line\">5</span><br><span class=\"line\">6</span><br><span class=\"line\">7</span><br><span class=\"line\">8</span><br><span class=\"line\">9</span><br><span class=\"line\">10</span><br><span class=\"line\">11</span><br><span class=\"line\">12</span><br><span class=\"line\">13</span><br><span class=\"line\">14</span><br><span class=\"line\">15</span><br><span class=\"line\">16</span><br><span class=\"line\">17</span><br><span class=\"line\">18</span><br><span class=\"line\">19</span><br><span class=\"line\">20</span><br><span class=\"line\">21</span><br><span class=\"line\">22</span><br></pre></td><td class=\"code\"><pre><span class=\"line\">&lt;?xml version=<span class=\"hljs-string\">\"1.0\"</span>?&gt;</span><br><span class=\"line\"><span class=\"hljs-language-xml\"><span class=\"hljs-tag\">&lt;<span class=\"hljs-name\">feed</span> <span class=\"hljs-attr\">xmlns</span>=<span class=\"hljs-string\">\"http://www.w3.org/2005/Atom\"</span>&gt;</span></span></span><br><span class=\"line\"><span class=\"hljs-language-xml\">    <span class=\"hljs-tag\">&lt;<span class=\"hljs-name\">id</span>&gt;</span>&lt;%= config.url %&gt;<span class=\"hljs-tag\">&lt;/<span class=\"hljs-name\">id</span>&gt;</span></span></span><br><span class=\"line\"><span class=\"hljs-language-xml\">    <span class=\"hljs-tag\">&lt;<span class=\"hljs-name\">title</span>&gt;</span>&lt;%= config.title %&gt;&lt;%= tag ? ` • Posts by \"${tag}\" tag` : '' %&gt;&lt;%= category ? ` • Posts by \"${category}\" category` : '' %&gt;<span class=\"hljs-tag\">&lt;/<span class=\"hljs-name\">title</span>&gt;</span></span></span><br><span class=\"line\"><span class=\"hljs-language-xml\">    <span class=\"hljs-tag\">&lt;<span class=\"hljs-name\">link</span> <span class=\"hljs-attr\">href</span>=<span class=\"hljs-string\">\"&lt;%= config.url %&gt;\"</span> /&gt;</span></span></span><br><span class=\"line\"><span class=\"hljs-language-xml\">    <span class=\"hljs-tag\">&lt;<span class=\"hljs-name\">updated</span>&gt;</span>&lt;%= moment(lastBuildDate).toISOString() %&gt;<span class=\"hljs-tag\">&lt;/<span class=\"hljs-name\">updated</span>&gt;</span></span></span><br><span class=\"line\"><span class=\"hljs-language-xml\">    &lt;%_ for (const { name } of (tags || [])) { _%&gt;</span></span><br><span class=\"line\"><span class=\"hljs-language-xml\">    <span class=\"hljs-tag\">&lt;<span class=\"hljs-name\">category</span> <span class=\"hljs-attr\">term</span>=<span class=\"hljs-string\">\"&lt;%= name %&gt;\"</span> /&gt;</span></span></span><br><span class=\"line\"><span class=\"hljs-language-xml\">    &lt;%_ } _%&gt;</span></span><br><span class=\"line\"><span class=\"hljs-language-xml\">    &lt;%_ for (const post of posts) { _%&gt;</span></span><br><span class=\"line\"><span class=\"hljs-language-xml\">    <span class=\"hljs-tag\">&lt;<span class=\"hljs-name\">entry</span>&gt;</span></span></span><br><span class=\"line\"><span class=\"hljs-language-xml\">        <span class=\"hljs-tag\">&lt;<span class=\"hljs-name\">id</span>&gt;</span>&lt;%= post.permalink %&gt;<span class=\"hljs-tag\">&lt;/<span class=\"hljs-name\">id</span>&gt;</span></span></span><br><span class=\"line\"><span class=\"hljs-language-xml\">        <span class=\"hljs-tag\">&lt;<span class=\"hljs-name\">title</span>&gt;</span>&lt;%= post.title %&gt;<span class=\"hljs-tag\">&lt;/<span class=\"hljs-name\">title</span>&gt;</span></span></span><br><span class=\"line\"><span class=\"hljs-language-xml\">        <span class=\"hljs-tag\">&lt;<span class=\"hljs-name\">link</span> <span class=\"hljs-attr\">rel</span>=<span class=\"hljs-string\">\"alternate\"</span> <span class=\"hljs-attr\">href</span>=<span class=\"hljs-string\">\"&lt;%= post.permalink %&gt;\"</span>/&gt;</span></span></span><br><span class=\"line\"><span class=\"hljs-language-xml\">        <span class=\"hljs-tag\">&lt;<span class=\"hljs-name\">content</span> <span class=\"hljs-attr\">type</span>=<span class=\"hljs-string\">\"html\"</span>&gt;</span>&lt;%= post.content %&gt;<span class=\"hljs-tag\">&lt;/<span class=\"hljs-name\">content</span>&gt;</span></span></span><br><span class=\"line\"><span class=\"hljs-language-xml\">        &lt;%_ for (const { name } of (post.tags ? post.tags.toArray() : [])) { _%&gt;</span></span><br><span class=\"line\"><span class=\"hljs-language-xml\">        <span class=\"hljs-tag\">&lt;<span class=\"hljs-name\">category</span> <span class=\"hljs-attr\">term</span>=<span class=\"hljs-string\">\"&lt;%= name %&gt;\"</span> /&gt;</span></span></span><br><span class=\"line\"><span class=\"hljs-language-xml\">        &lt;%_ } _%&gt;</span></span><br><span class=\"line\"><span class=\"hljs-language-xml\">        <span class=\"hljs-tag\">&lt;<span class=\"hljs-name\">updated</span>&gt;</span>&lt;%= moment(post.date).toISOString() %&gt;<span class=\"hljs-tag\">&lt;/<span class=\"hljs-name\">updated</span>&gt;</span></span></span><br><span class=\"line\"><span class=\"hljs-language-xml\">    <span class=\"hljs-tag\">&lt;/<span class=\"hljs-name\">entry</span>&gt;</span></span></span><br><span class=\"line\"><span class=\"hljs-language-xml\">    &lt;%_ } _%&gt;</span></span><br><span class=\"line\"><span class=\"hljs-language-xml\"><span class=\"hljs-tag\">&lt;/<span class=\"hljs-name\">feed</span>&gt;</span></span></span><br></pre></td></tr></tbody></table></figure></body></html>",
            "tags": [
                "rss",
                "hexo"
            ]
        }
    ]
}